isporn/classifier.py
isporn/__init__.py
isporn-0.9.1.dist-info/top_level.txt
isporn-0.9.1.dist-info/METADATA
isporn-0.9.1.dist-info/RECORD
isporn-0.9.1.dist-info/metadata.json
isporn-0.9.1.dist-info/DESCRIPTION.rst
isporn-0.9.1.dist-info/WHEEL
