Metadata-Version: 2.0
Name: isporn
Version: 0.9.1
Summary: A module to identify if a picture is porn
Home-page: http://exadeep.com
Author: Exadeep
Author-email: service@exadeep.com
License: MIT
Keywords: Tag Porn Picture
Platform: UNKNOWN
Classifier: Development Status :: 5 - Production/Stable
Classifier: Intended Audience :: Developers
Classifier: License :: OSI Approved :: MIT License
Classifier: Programming Language :: Python :: 2.6
Classifier: Programming Language :: Python :: 2.7
Classifier: Programming Language :: Python :: 3
Classifier: Programming Language :: Python :: 3.3
Classifier: Programming Language :: Python :: 3.4
Requires-Dist: pillow
Requires-Dist: requests
Requires-Dist: simplejson
Requires-Dist: pyOpenSSL
Requires-Dist: ndg-httpsclient
Requires-Dist: pyasn1
